commandsniffer/__init__.py
commandsniffer/__main__.py
commandsniffer/graph.py
commandsniffer/interceptor.py
commandsniffer/utils.py
command_sniffer-2024.12.dist-info/LICENSE
command_sniffer-2024.12.dist-info/METADATA
command_sniffer-2024.12.dist-info/WHEEL
command_sniffer-2024.12.dist-info/entry_points.txt
command_sniffer-2024.12.dist-info/top_level.txt
command_sniffer-2024.12.dist-info/RECORD
