Metadata-Version: 2.1
Name: command-sniffer
Version: 2024.12
Summary: A light-weighted tool to intercept commands during execution of a program
Classifier: Development Status :: 3 - Alpha
Classifier: Programming Language :: Python :: 3
Requires-Python: >=3.8
License-File: LICENSE
Requires-Dist: loguru
Requires-Dist: pydantic
Provides-Extra: dev
Requires-Dist: pycodestyle; extra == "dev"
Requires-Dist: mypy; extra == "dev"
